{
    "@context": "https://schema.org",
    "@type": "LocalBusiness",
    "name": "Автохимчистка Хайземберг",
    "alternateName": "Химчистка Хайземберг",
    "description": "Профессиональная автохимчистка в Кисловодске. Химчистка салона автомобиля, чистка салона авто, сухой туман для устранения запахов. Качественная автохимчистка недорого.",
    "url": "https://heisenbergclean.ru",
    "telephone": "+7 (933) 330-33-31",
    "address": {
        "@type": "PostalAddress",
        "streetAddress": "ул. Боргустанская, 7",
        "addressLocality": "Кисловодск",
        "addressRegion": "Ставропольский край",
        "postalCode": "357736",
        "addressCountry": "RU"
    },
    "geo": {
        "@type": "GeoCoordinates",
        "latitude": "43.922291",
        "longitude": "42.712772"
    },
    "openingHoursSpecification": [
        {
            "@type": "OpeningHoursSpecification",
            "dayOfWeek": ["Monday", "Tuesday", "Wednesday", "Thursday", "Friday", "Saturday"],
            "opens": "09:00",
            "closes": "21:00"
        }
    ],
    "image": "https://heisemberg.vercel.app/Main.svg",
    "logo": "https://heisemberg.vercel.app/Main.svg",
    "sameAs": [
        "https://wa.me/79333303331"
    ],
    "priceRange": "$$",
    "paymentAccepted": ["Cash", "Credit Card", "Bank Transfer"],
    "currenciesAccepted": "RUB",
    "areaServed": {
        "@type": "City",
        "name": "Кисловодск"
    },
    "hasOfferCatalog": {
        "@type": "OfferCatalog",
        "name": "Услуги автохимчистки в Кисловодске",
        "itemListElement": [
            {
                "@type": "Offer",
                "itemOffered": {
                    "@type": "Service",
                    "name": "Химчистка салона автомобиля",
                    "description": "Глубокая очистка всех поверхностей салона: сиденья, коврики, потолок, дверные панели с использованием профессиональных средств"
                }
            },
            {
                "@type": "Offer",
                "itemOffered": {
                    "@type": "Service",
                    "name": "Премиум-услуга",
                    "description": "Полная химчистка мягкой мебели с выездом на дом"
                }
            },
            {
                "@type": "Offer",
                "itemOffered": {
                    "@type": "Service",
                    "name": "Сухой туман",
                    "description": "Применяем технологию устранения неприятных запахов, бактерий и вирусов"
                }
            }
        ]
    },
    "aggregateRating": {
        "@type": "AggregateRating",
        "ratingValue": "4.9",
        "reviewCount": "127",
        "bestRating": "5",
        "worstRating": "1"
    },
    "review": [
        {
            "@type": "Review",
            "author": {
                "@type": "Person",
                "name": "Александр Петров"
            },
            "reviewRating": {
                "@type": "Rating",
                "ratingValue": "5",
                "bestRating": "5"
            },
            "reviewBody": "Отличная химчистка! Машина как новая после обработки. Рекомендую!"
        },
        {
            "@type": "Review",
            "author": {
                "@type": "Person",
                "name": "Мария Иванова"
            },
            "reviewRating": {
                "@type": "Rating",
                "ratingValue": "5",
                "bestRating": "5"
            },
            "reviewBody": "Быстро, качественно, недорого. Очень довольна результатом."
        }
    ]
}
